nonparametricdensity/__init__.py
nonparametricdensity/__version__.py
nonparametricdensity/base_estimator.py
nonparametricdensity/kernels.py
nonparametricdensity/univariate/__init__.py
nonparametricdensity/univariate/kernel_density_estimator.py
nonparametricdensity/utils/__init__.py
nonparametricdensity/utils/exceptions.py
nonparametricdensity/utils/gpuoptional.py
nonparametricdensity/utils/validators.py
NonParametricDensity-0.0.1.dist-info/LICENSE
NonParametricDensity-0.0.1.dist-info/METADATA
NonParametricDensity-0.0.1.dist-info/WHEEL
NonParametricDensity-0.0.1.dist-info/top_level.txt
NonParametricDensity-0.0.1.dist-info/RECORD
