Metadata-Version: 2.1
Name: NonParametricDensity
Version: 0.0.1
Summary: Python module for nonparametric density estimation with GPU support.
Home-page: https://github.com/GrzegorzMika/DensityEstimation/
Author: Grzegorz Mika
Author-email: g.w.mika@gmail.com
License: MIT
Platform: UNKNOWN
Classifier: License :: OSI Approved :: MIT License
Classifier: Programming Language :: Python
Classifier: Programming Language :: Python :: 3
Classifier: Programming Language :: Python :: 3.6
Classifier: Programming Language :: Python :: 3.7
Classifier: Programming Language :: Python :: 3.8
Classifier: Programming Language :: Python :: Implementation :: CPython
Classifier: Programming Language :: Python :: Implementation :: PyPy
Requires-Python: >=3.6
Requires-Dist: numpy
Provides-Extra: gpu_support
Requires-Dist: cupy ; extra == 'gpu_support'
